metaworld/__init__.py
metaworld/asset_path_utils.py
metaworld/env_dict.py
metaworld/evaluation.py
metaworld/py.typed
metaworld/sawyer_xyz_env.py
metaworld/types.py
metaworld/wrappers.py
metaworld/assets/objects/assembly_peg.xml
metaworld/assets/objects/basketball.xml
metaworld/assets/objects/basketballhoop.xml
metaworld/assets/objects/binA.xml
metaworld/assets/objects/binB.xml
metaworld/assets/objects/block.xml
metaworld/assets/objects/block_cyl.xml
metaworld/assets/objects/box.xml
metaworld/assets/objects/buttonbox.xml
metaworld/assets/objects/club.xml
metaworld/assets/objects/coffeemachine.xml
metaworld/assets/objects/dial.xml
metaworld/assets/objects/doorlockA.xml
metaworld/assets/objects/doorlockB.xml
metaworld/assets/objects/drawer.xml
metaworld/assets/objects/faucet.xml
metaworld/assets/objects/hammer.xml
metaworld/assets/objects/hammerblock.xml
metaworld/assets/objects/handle_press.xml
metaworld/assets/objects/laptop.xml
metaworld/assets/objects/lever.xml
metaworld/assets/objects/mug.xml
metaworld/assets/objects/objA.xml
metaworld/assets/objects/peg_block.xml
metaworld/assets/objects/peg_insert.xml
metaworld/assets/objects/plug.xml
metaworld/assets/objects/plug_wall.xml
metaworld/assets/objects/puck.xml
metaworld/assets/objects/puck_goal.xml
metaworld/assets/objects/shelf.xml
metaworld/assets/objects/shelfb.xml
metaworld/assets/objects/soccer_ball.xml
metaworld/assets/objects/soccer_goal.xml
metaworld/assets/objects/sphere.xml
metaworld/assets/objects/stick.xml
metaworld/assets/objects/table.xml
metaworld/assets/objects/table_hole.xml
metaworld/assets/objects/thermos.xml
metaworld/assets/objects/wall.xml
metaworld/assets/objects/window.xml
metaworld/assets/objects/window_horiz.xml
metaworld/assets/objects/xyz_base.xml
metaworld/assets/objects/assets/assembly_peg.xml
metaworld/assets/objects/assets/assembly_peg_dependencies.xml
metaworld/assets/objects/assets/basketball.xml
metaworld/assets/objects/assets/basketball_dependencies.xml
metaworld-3.0.0.dist-info/licenses/LICENSE
metaworld-3.0.0.dist-info/METADATA
metaworld-3.0.0.dist-info/WHEEL
metaworld-3.0.0.dist-info/top_level.txt
metaworld-3.0.0.dist-info/RECORD
