Metadata-Version: 2.4
Name: metaworld
Version: 3.0.0
Summary: Collections of robotics environments geared towards benchmarking multi-task and meta reinforcement learning.
Author-email: Farama Foundation <contact@farama.org>
License: MIT License
Project-URL: Homepage, https://farama.org
Project-URL: Repository, https://github.com/Farama-Foundation/Metaworld
Project-URL: Documentation, https://metaworld.github.io/
Project-URL: Bug Report, https://github.com/Farama-Foundation/Metaworld/issues
Keywords: Reinforcement Learning,game,RL,AI,gymnasium
Classifier: Development Status :: 4 - Beta
Classifier: License :: OSI Approved :: MIT License
Classifier: Programming Language :: Python :: 3
Classifier: Programming Language :: Python :: 3.8
Classifier: Programming Language :: Python :: 3.9
Classifier: Programming Language :: Python :: 3.10
Classifier: Programming Language :: Python :: 3.11
Classifier: Intended Audience :: Science/Research
Classifier: Topic :: Scientific/Engineering :: Artificial Intelligence
Requires-Python: >=3.10
License-File: LICENSE
Requires-Dist: gymnasium>=1.1
Requires-Dist: mujoco>=3.0.0
Requires-Dist: numpy>=1.18
Requires-Dist: scipy>=1.4.1
Requires-Dist: imageio
Provides-Extra: testing
Requires-Dist: ipdb; extra == "testing"
Requires-Dist: memory_profiler; extra == "testing"
Requires-Dist: pyquaternion==0.9.5; extra == "testing"
Requires-Dist: pytest>=4.4.0; extra == "testing"
Provides-Extra: dev
Requires-Dist: black; extra == "dev"
Requires-Dist: isort; extra == "dev"
Requires-Dist: mypy; extra == "dev"
Dynamic: license-file
